justautomate/__init__.py
justautomate/_nbdev.py
justautomate/cli.py
justautomate/tools/__init__.py
justautomate/tools/security.py
justautomate-0.0.1.dist-info/LICENSE
justautomate-0.0.1.dist-info/METADATA
justautomate-0.0.1.dist-info/WHEEL
justautomate-0.0.1.dist-info/entry_points.txt
justautomate-0.0.1.dist-info/top_level.txt
justautomate-0.0.1.dist-info/RECORD
