Metadata-Version: 2.1
Name: justautomate
Version: 0.0.1
Summary: JustAutomate.co CLI
Home-page: https://github.com/justautomate-co/justautomate
Author: Justin Mitchel
Author-email: hello@teamcfe.com
License: Apache Software License 2.0
Keywords: automation,lowcode,nocode
Platform: UNKNOWN
Classifier: Development Status :: 3 - Alpha
Classifier: Intended Audience :: Developers
Classifier: Natural Language :: English
Classifier: Programming Language :: Python :: 3.6
Classifier: Programming Language :: Python :: 3.7
Classifier: Programming Language :: Python :: 3.8
Classifier: License :: OSI Approved :: Apache Software License
Requires-Python: >=3.6
Requires-Dist: pip
Requires-Dist: packaging
Requires-Dist: fire (<0.5.0,>=0.4.0)
Provides-Extra: dev
